opendss_mcp/__init__.py
opendss_mcp/server.py
opendss_mcp/data/__init__.py
opendss_mcp/data/download_official_feeders.py
opendss_mcp/data/control_curves/__init__.py
opendss_mcp/data/ieee_feeders/__init__.py
opendss_mcp/data/load_profiles/__init__.py
opendss_mcp/tools/__init__.py
opendss_mcp/tools/capacity.py
opendss_mcp/tools/der_optimizer.py
opendss_mcp/tools/feeder_loader.py
opendss_mcp/tools/power_flow.py
opendss_mcp/tools/timeseries.py
opendss_mcp/tools/visualization.py
opendss_mcp/tools/voltage_checker.py
opendss_mcp/utils/__init__.py
opendss_mcp/utils/dss_wrapper.py
opendss_mcp/utils/formatters.py
opendss_mcp/utils/harmonics.py
opendss_mcp/utils/inverter_control.py
opendss_mcp/utils/validators.py
opendss_mcp_server-1.0.0.dist-info/licenses/LICENSE
opendss_mcp_server-1.0.0.dist-info/METADATA
opendss_mcp_server-1.0.0.dist-info/WHEEL
opendss_mcp_server-1.0.0.dist-info/top_level.txt
opendss_mcp_server-1.0.0.dist-info/RECORD
