Metadata-Version: 2.4
Name: opendss-mcp-server
Version: 1.0.0
Summary: Model Context Protocol server for EPRI's OpenDSS power system simulator - enabling AI-powered distribution system analysis
Author-email: Ahmed Elshazly <ahmedelshazly27@gmail.com>
License-Expression: MIT
Project-URL: Homepage, https://github.com/ahmedelshazly27/opendss-mcp-server
Project-URL: Documentation, https://github.com/ahmedelshazly27/opendss-mcp-server#readme
Project-URL: Repository, https://github.com/ahmedelshazly27/opendss-mcp-server
Project-URL: Bug Tracker, https://github.com/ahmedelshazly27/opendss-mcp-server/issues
Project-URL: Source Code, https://github.com/ahmedelshazly27/opendss-mcp-server
Project-URL: Changelog, https://github.com/ahmedelshazly27/opendss-mcp-server/releases
Keywords: power-systems,opendss,mcp,energy,distribution,electrical-engineering,power-flow,der,ai,claude
Classifier: Development Status :: 5 - Production/Stable
Classifier: Intended Audience :: Science/Research
Classifier: Intended Audience :: Developers
Classifier: Topic :: Scientific/Engineering
Classifier: Topic :: Scientific/Engineering :: Physics
Classifier: Topic :: Software Development :: Libraries :: Python Modules
Classifier: Programming Language :: Python :: 3
Classifier: Programming Language :: Python :: 3.10
Classifier: Programming Language :: Python :: 3.11
Classifier: Programming Language :: Python :: 3.12
Classifier: Programming Language :: Python :: 3.13
Classifier: Operating System :: OS Independent
Classifier: Operating System :: POSIX :: Linux
Classifier: Operating System :: MacOS
Classifier: Operating System :: Microsoft :: Windows
Classifier: Framework :: Pytest
Classifier: Natural Language :: English
Requires-Python: >=3.10
License-File: LICENSE
Requires-Dist: mcp>=0.9.0
Requires-Dist: opendssdirect.py>=0.8.4
Requires-Dist: pandas>=2.0.0
Requires-Dist: numpy>=1.24.0
Requires-Dist: matplotlib>=3.7.0
Requires-Dist: networkx>=3.1
Provides-Extra: dev
Requires-Dist: pytest>=7.4.0; extra == "dev"
Requires-Dist: pytest-cov>=4.1.0; extra == "dev"
Requires-Dist: pytest-anyio>=0.0.0; extra == "dev"
Requires-Dist: black>=23.0.0; extra == "dev"
Requires-Dist: pylint>=2.17.0; extra == "dev"
Requires-Dist: mypy>=1.4.0; extra == "dev"
Provides-Extra: test
Requires-Dist: pytest>=7.4.0; extra == "test"
Requires-Dist: pytest-cov>=4.1.0; extra == "test"
Requires-Dist: pytest-anyio>=0.0.0; extra == "test"
Provides-Extra: docs
Requires-Dist: sphinx>=7.0.0; extra == "docs"
Requires-Dist: sphinx-rtd-theme>=1.3.0; extra == "docs"
Provides-Extra: all
Requires-Dist: pytest>=7.4.0; extra == "all"
Requires-Dist: pytest-cov>=4.1.0; extra == "all"
Requires-Dist: pytest-anyio>=0.0.0; extra == "all"
Requires-Dist: black>=23.0.0; extra == "all"
Requires-Dist: pylint>=2.17.0; extra == "all"
Requires-Dist: mypy>=1.4.0; extra == "all"
Requires-Dist: sphinx>=7.0.0; extra == "all"
Requires-Dist: sphinx-rtd-theme>=1.3.0; extra == "all"
Dynamic: license-file
